skymap_convert/__init__.py
skymap_convert/_version.py
skymap_convert/plotting.py
skymap_convert/presets.py
skymap_convert/skymap_readers.py
skymap_convert/skymap_writers.py
skymap_convert/utils.py
skymap_convert/_internal/__init__.py
skymap_convert/_internal/examples.py
skymap_convert/converted_skymaps/lsst_skymap/metadata.yaml
skymap_convert/converted_skymaps/lsst_skymap/patches.npy.gz
skymap_convert/converted_skymaps/lsst_skymap/tracts.npy
skymap_convert-0.1.1.dist-info/licenses/LICENSE
skymap_convert-0.1.1.dist-info/METADATA
skymap_convert-0.1.1.dist-info/WHEEL
skymap_convert-0.1.1.dist-info/top_level.txt
skymap_convert-0.1.1.dist-info/RECORD
