Metadata-Version: 2.4
Name: skymap_convert
Version: 0.1.1
Author-email: Olivia Lynn <olynn@andrew.cmu.edu>
License: MIT License
Project-URL: Source Code, https://github.com/lincc-frameworks/skymap_convert
Classifier: Development Status :: 4 - Beta
Classifier: License :: OSI Approved :: MIT License
Classifier: Intended Audience :: Developers
Classifier: Intended Audience :: Science/Research
Classifier: Operating System :: OS Independent
Classifier: Programming Language :: Python
Requires-Python: >=3.10
License-File: LICENSE
Requires-Dist: numpy>=1.21
Requires-Dist: astropy>=5.0
Requires-Dist: matplotlib>=3.4
Provides-Extra: dev
Requires-Dist: lsst-sphgeom; (sys_platform == "darwin" or sys_platform == "linux") and extra == "dev"
Requires-Dist: jupyter; extra == "dev"
Requires-Dist: pre-commit; extra == "dev"
Requires-Dist: ruff; extra == "dev"
Requires-Dist: pytest; extra == "dev"
Requires-Dist: pytest-cov; extra == "dev"
Requires-Dist: pytest-skip-slow; extra == "dev"
Requires-Dist: tqdm; extra == "dev"
Requires-Dist: lsdb; extra == "dev"
Requires-Dist: dask; extra == "dev"
Dynamic: license-file
